piipaa/__init__.py
piipaa/__main__.py
piipaa/_version.py
piipaa/cli.py
piipaa/data.json
piipaa/piipaa.py
piipaa-2022.5.1.dist-info/LICENSE
piipaa-2022.5.1.dist-info/METADATA
piipaa-2022.5.1.dist-info/WHEEL
piipaa-2022.5.1.dist-info/entry_points.txt
piipaa-2022.5.1.dist-info/top_level.txt
piipaa-2022.5.1.dist-info/RECORD
