Metadata-Version: 2.1
Name: piipaa
Version: 2022.5.1
Summary: Python Installs Python anywhere.
Home-page: https://github.com/sthagen/piipaa
Author: Stefan Hagen
Author-email: "Stefan Hagen" <stefan@hagen.link>
License: MIT
Platform: UNKNOWN
Classifier: License :: OSI Approved :: MIT License
Requires-Python: >=3.8
License-File: LICENSE
